{
  "description": "Buat prompt untuk NightCafe Creator, dengan mempertimbangkan model dan preset gayanya.",
  "toolType": "image-generation",
  "ai_logic_description": "Persona AI: Anda adalah seorang Kurator Seni AI yang akan menghasilkan karya seni berdasarkan prompt utama.",
  "components": [
    {
      "name": "mainPrompt",
      "label": "Prompt Utama",
      "type": "textarea",
      "placeholder": "e.g., 'The celestial wolf, cosmic dust, stars, nebula, vibrant colors'",
      "info": "Deskripsi utama dari karya seni Anda.",
      "validation": {
        "min_length": 20
      }
    },
    {
      "name": "stylePreset",
      "label": "Preset Gaya",
      "type": "text",
      "placeholder": "e.g., 'Cosmic', 'Oil Painting', 'Cyberpunk'",
      "info": "Gaya preset yang Anda pilih di NightCafe.",
      "validation": {
        "min_length": 3
      }
    },
    {
      "name": "model",
      "label": "Model AI",
      "type": "text",
      "placeholder": "e.g., 'SDXL 1.0', 'DALL-E 3'",
      "info": "Model dasar yang digunakan untuk generasi.",
      "validation": {
        "min_length": 3
      }
    },
    {
      "name": "negativePrompt",
      "label": "Prompt Negatif",
      "type": "text",
      "placeholder": "e.g., 'low resolution, dull colors'",
      "info": "Elemen yang ingin dihindari.",
      "optional": true,
      "validation": {
        "min_length": 5
      }
    },
    {
      "name": "additionalContext",
      "label": "Konteks Tambahan & Instruksi Khusus",
      "type": "textarea",
      "placeholder": "Contoh: Gunakan gaya bahasa yang sangat personal dan rentan. Sertakan satu analogi tentang berkebun. Akhiri dengan nada yang penuh harapan.",
      "info": "Instruksi spesifik tentang gaya, nada, atau elemen naratif yang harus ada.",
      "optional": true,
      "validation": {
        "min_length": 10
      }
    }
  ],
  "kategori": [
    "Gambar & Desain",
    "Prompt AI Gambar (Text-to-Image)"
  ],
  "nama_kerangka": "NightCafe",
  "examples": [],
  "temperature": 0.7,
  "top_p": 0.9,
  "top_k": 40,
  "version": "2.0.0",
  "updated_at": "2025-12-23T06:05:33.648749",
  "komponen_prompt": {
    "PERAN": "Persona AI: Anda adalah seorang Kurator Seni AI yang akan menghasilkan karya seni berdasarkan prompt utama.",
    "KONTEKS": "Prompt Utama: {{mainPrompt}} Preset Gaya: {{stylePreset}} Model AI: {{model}} [Prompt Negatif: {{negativePrompt}}] [Konteks Tambahan & Instruksi Khusus: {{additionalContext}}]",
    "TUGAS": "Generate prompt visual yang menghasilkan image/video sesuai dengan deskripsi, style, dan parameter yang diminta.",
    "FORMAT_OUTPUT": "Sajikan prompt dalam format yang optimal untuk AI image/video generation, dengan detail visual yang jelas dan technical parameters yang sesuai."
  },
  "_review_notes": [
    "TODO: Consider adding conditional blocks [...] for optional parameters"
  ]
}